aryn_mcp_server/__init__.py
aryn_mcp_server/aryn_docset_manager.py
aryn_mcp_server/aryn_document_manager.py
aryn_mcp_server/aryn_mcp_server.py
aryn_mcp_server/models/__init__.py
aryn_mcp_server/models/add_aryn_document_model.py
aryn_mcp_server/models/create_aryn_docset_model.py
aryn_mcp_server/models/delete_aryn_docset_model.py
aryn_mcp_server/models/delete_aryn_docset_properties_model.py
aryn_mcp_server/models/delete_aryn_document_model.py
aryn_mcp_server/models/document_schema.py
aryn_mcp_server/models/draw_boxes_model.py
aryn_mcp_server/models/extract_aryn_document_properties_model.py
aryn_mcp_server/models/get_aryn_docset_model.py
aryn_mcp_server/models/get_aryn_document_components_model.py
aryn_mcp_server/models/get_aryn_document_extracted_properties_model.py
aryn_mcp_server/models/list_aryn_docsets_model.py
aryn_mcp_server/models/list_aryn_documents_model.py
aryn_mcp_server/models/partition_model.py
aryn_mcp_server/models/properties_filter_model.py
aryn_mcp_server/models/query_aryn_docset_model.py
aryn_mcp_server/models/search_aryn_docset_model.py
aryn_mcp_server/utils/__init__.py
aryn_mcp_server/utils/utils.py
aryn_mcp_server-0.1.13.dist-info/licenses/LICENSE
aryn_mcp_server-0.1.13.dist-info/WHEEL
aryn_mcp_server-0.1.13.dist-info/entry_points.txt
aryn_mcp_server-0.1.13.dist-info/METADATA
aryn_mcp_server-0.1.13.dist-info/RECORD
