Metadata-Version: 2.4
Name: aryn-mcp-server
Version: 0.1.13
Summary: The Official Local Aryn MCP Server
Author: Aryn AI
Author-email: Aryn AI <info@aryn.ai>
License-Expression: Apache-2.0
License-File: LICENSE
Classifier: Programming Language :: Python :: 3
Classifier: Operating System :: OS Independent
Requires-Dist: mcp>=1.9.4,<2.0.0
Requires-Dist: pillow>=11.2.1,<12.0.0
Requires-Dist: pydantic>=2.11.7,<3.0.0
Requires-Dist: aryn-sdk>=0.2.12,<0.3.0
Requires-Python: >=3.12
